CHANGELOG.txt
LICENSE
MANIFEST.in
README.md
setup.py
BasicCalculatorFasil/BasicCalculatorFasil.py
BasicCalculatorFasil/__init__.py
BasicCalculatorFasil.egg-info/PKG-INFO
BasicCalculatorFasil.egg-info/SOURCES.txt
BasicCalculatorFasil.egg-info/dependency_links.txt
BasicCalculatorFasil.egg-info/requires.txt
BasicCalculatorFasil.egg-info/top_level.txt
test/tests_BasicCalculatorFasil.py