Metadata-Version: 2.1
Name: BasicCalculatorFasil
Version: 0.0.4
Summary: Simple calculator
Home-page: https://github.com/FasilGibdaw/BasicCalculatorFasil/
Author: FasilGibdaw (Fasil Kebede)
Author-email: <fasgibda@gmail.com>
License: MIT
Keywords: python
Classifier: Development Status :: 1 - Planning
Classifier: Intended Audience :: Developers
Classifier: Programming Language :: Python :: 3
Classifier: Operating System :: Unix
Classifier: Operating System :: MacOS :: MacOS X
Classifier: Operating System :: Microsoft :: Windows
License-File: LICENSE
